open_gpias/ConfigEditor.py
open_gpias/MeasurementPlot.py
open_gpias/SignalEditor.py
open_gpias/StimulusBackend.py
open_gpias/StimulusFrontEnd.py
open_gpias/__init__.py
open_gpias/equalizer.py
open_gpias/gui_helpers.py
open_gpias/icon.ico
open_gpias/mainWindow.py
open_gpias/soundSignal.py
open_gpias/start.py
open_gpias-0.9.0.dist-info/METADATA
open_gpias-0.9.0.dist-info/WHEEL
open_gpias-0.9.0.dist-info/entry_points.txt
open_gpias-0.9.0.dist-info/top_level.txt
open_gpias-0.9.0.dist-info/RECORD
