Metadata-Version: 2.1
Name: open-gpias
Version: 0.9.0
Summary: Open GPIAS to measure startle responses
Home-page: https://bitbucket.org/randrian/asr_setup
Author: Hinrich Rahlfs, Matthias Streb, Achim Schilling, Richard Gerum
Author-email: richard.gerum@fau.de
License: GPLv3
Platform: UNKNOWN
Requires-Dist: sounddevice
Requires-Dist: scipy
Requires-Dist: matplotlib
Requires-Dist: qtpy
Requires-Dist: PyDAQmx
Requires-Dist: pandas
